[{"name": "r_1000.torrent", "link": "http://libgen.rs/repository_torrent/r_1000.torrent", "created_unix": 1236963056, "size_bytes": 5102653477, "type": "books", "infohash": "ff0bcba08ef0886a512032c037e6b065d9c5c458", "seeders": 14, "leechers": 0, "completed": 338, "scraped_date": 1625078869, "dht_peers": 0, "dht_scraped": null}, {"name": "r_2000.torrent", "link": "http://libgen.rs/repository_torrent/r_2000.torrent", "created_unix": 1236963278, "size_bytes": 7195274864, "type": "books", "infohash": "b73676a3d32a59a88e35eab35ab271900be60303", "seeders": 7, "leechers": 0, "completed": 167, "scraped_date": 1625078869, "dht_peers": 0, "dht_scraped": null}, {"name": "r_3000.torrent", "link": "http://libgen.rs/repository_torrent/r_3000.torrent", "created_unix": 1236963801, "size_bytes": 3979343217, "type": "books", "infohash": "c9b9f8bf46913bb2f89294fed74c2dd879f9acef", "seeders": 8, "leechers": 0, "completed": 142, "scraped_date": 1625078869, "dht_peers": 0, "dht_scraped": null}, {"name": "r_4000.torrent", "link": "http://libgen.rs/repository_torrent/r_4000.torrent", "created_unix": 1236963992, "size_bytes": 3419142513, "type": "books", "infohash": "9bf8c28967e481df5585291510550ef354ea91ec", "seeders": 11, "leechers": 0, "completed": 171, "scraped_date": 1625078869, "dht_peers": 0, "dht_scraped": null}, {"name": "r_5000.torrent", "link": "http://libgen.rs/repository_torrent/r_5000.torrent", "created_unix": 1236964114, "size_bytes": 3464609645, "type": "books", "infohash": "b317dba1d3bf839486272f8779783ffcd1c52512", "seeders": 6, "leechers": 0, "completed": 137, "scraped_date": 1625078869, "dht_peers": 0, "dht_scraped": null}, {"name": "r_6000.torrent", "link": "http://libgen.rs/repository_torrent/r_6000.torrent", "created_unix": 1236964274, "size_bytes": 3758609738, "type": "books", "infohash": "ec8aac6cd38772ffd365529b855da8840211f6c4", "seeders": 8, "leechers": 0, "completed": 127, "scraped_date": 1625078869, "dht_peers": 0, "dht_scraped": null}, {"name": "r_7000.torrent", "link": "http://libgen.rs/repository_torrent/r_7000.torrent", "created_unix": 1236964492, "size_bytes": 3425806839, "type": "books", "infohash": "1ef6d2c7ee7de896ed93648930be45bfb0d1d0b9", "seeders": 8, "leechers": 0, "completed": 119, "scraped_date": 1625078869, "dht_peers": 0, "dht_scraped": null}, {"name": "r_8000.torrent", "link": "http://libgen.rs/repository_torrent/r_8000.torrent", "created_unix": 1236964623, "size_bytes": 4401080350, "type": "books", "infohash": "34499f3e0d67aad1d5f0b1cfd23fc67c8c1573a6", "seeders": 7, "leechers": 0, "completed": 113, "scraped_date": 1625078869, "dht_peers": 0, "dht_scraped": null}, {"name": "r_9000.torrent", "link": "http://libgen.rs/repository_torrent/r_9000.torrent", "created_unix": 1236964771, "size_bytes": 3798220614, "type": "books", "infohash": "0c1df03c29617cb23f67a6ab9de615bab869b53e", "seeders": 9, "leechers": 1, "completed": 112, "scraped_date": 1625078869, "dht_peers": 0, "dht_scraped": null}, {"name": "r_10000.torrent", "link": "http://libgen.rs/repository_torrent/r_10000.torrent", "created_unix": 1236964918, "size_bytes": 3605339634, "type": "books", "infohash": "1a9c625bde1eb7bc4c77c264748786bb46520162", "seeders": 9, "leechers": 0, "completed": 142, "scraped_date": 1625078869, "dht_peers": 0, "dht_scraped": null}, {"name": "r_11000.torrent", "link": "http://libgen.rs/repository_torrent/r_11000.torrent", "created_unix": 1236965005, "size_bytes": 2787276540, "type": "books", "infohash": "b03e676d9412839c968fdb5e9d39d18388c7d8dd", "seeders": 8, "leechers": 0, "completed": 109, "scraped_date": 1625078869, "dht_peers": 0, "dht_scraped": null}, {"name": "r_12000.torrent", "link": "http://libgen.rs/repository_torrent/r_12000.torrent", "created_unix": 1236965147, "size_bytes": 4402168751, "type": "books", "infohash": "d75206d214e655066d790dec34940967b61503f2", "seeders": 8, "leechers": 0, "completed": 112, "scraped_date": 1625078869, "dht_peers": 0, "dht_scraped": null}, {"name": "r_13000.torrent", "link": "http://libgen.rs/repository_torrent/r_13000.torrent", "created_unix": 1236965710, "size_bytes": 5157055982, "type": "books", "infohash": "de9d1872bb2c2c400f1d415da347a86973c53b73", "seeders": 8, "leechers": 0, "completed": 108, "scraped_date": 1625078869, "dht_peers": 0, "dht_scraped": null}, {"name": "r_14000.torrent", "link": "http://libgen.rs/repository_torrent/r_14000.torrent", "created_unix": 1236966062, "size_bytes": 5891687748, "type": "books", "infohash": "bccfe2061642bfd81044acb4230dc4569dcb697e", "seeders": 8, "leechers": 0, "completed": 108, "scraped_date": 1625078869, "dht_peers": 0, "dht_scraped": null}, {"name": "r_15000.torrent", "link": "http://libgen.rs/repository_torrent/r_15000.torrent", "created_unix": 1236966380, "size_bytes": 4797082817, "type": "books", "infohash": "296069fa2cd45637269691418d683d0ec56ad85b", "seeders": 6, "leechers": 0, "completed": 92, "scraped_date": 1625078869, "dht_peers": 0, "dht_scraped": null}, {"name": "r_16000.torrent", "link": "http://libgen.rs/repository_torrent/r_16000.torrent", "created_unix": 1236967076, "size_bytes": 3144192376, "type": "books", "infohash": "be97303240793af9b55544e1123087bb191303b0", "seeders": 5, "leechers": 0, "completed": 101, "scraped_date": 1625078869, "dht_peers": 0, "dht_scraped": null}, {"name": "r_17000.torrent", "link": "http://libgen.rs/repository_torrent/r_17000.torrent", "created_unix": 1236967246, "size_bytes": 4540181136, "type": "books", "infohash": "bfd18e124064617dc4f1a6feb24632df0a9101c4", "seeders": 7, "leechers": 0, "completed": 85, "scraped_date": 1625078869, "dht_peers": 0, "dht_scraped": null}, {"name": "r_18000.torrent", "link": "http://libgen.rs/repository_torrent/r_18000.torrent", "created_unix": 1236967359, "size_bytes": 3345688654, "type": "books", "infohash": "2080e6599450c278998c4aa779c1cbd8b447d891", "seeders": 8, "leechers": 0, "completed": 105, "scraped_date": 1625078869, "dht_peers": 0, "dht_scraped": null}, {"name": "r_19000.torrent", "link": "http://libgen.rs/repository_torrent/r_19000.torrent", "created_unix": 1236967534, "size_bytes": 1899320017, "type": "books", "infohash": "e3a3176cb86f885b3ec7cc322fe2e69220831cd0", "seeders": 7, "leechers": 0, "completed": 96, "scraped_date": 1625078869, "dht_peers": 0, "dht_scraped": null}, {"name": "r_20000.torrent", "link": "http://libgen.rs/repository_torrent/r_20000.torrent", "created_unix": 1236967582, "size_bytes": 242888098, "type": "books", "infohash": "44a734a87c536470c349f01c3d590e1f8aec0a74", "seeders": 7, "leechers": 0, "completed": 96, "scraped_date": 1625078869, "dht_peers": 0, "dht_scraped": null}]